setup.py
datahog/__init__.py
datahog/error.py
datahog/pool.py
datahog.egg-info/PKG-INFO
datahog.egg-info/SOURCES.txt
datahog.egg-info/dependency_links.txt
datahog.egg-info/requires.txt
datahog.egg-info/top_level.txt
datahog/api/__init__.py
datahog/api/alias.py
datahog/api/entity.py
datahog/api/name.py
datahog/api/node.py
datahog/api/prop.py
datahog/api/relationship.py
datahog/const/__init__.py
datahog/const/context.py
datahog/const/flag.py
datahog/const/search.py
datahog/const/storage.py
datahog/const/table.py
datahog/const/util.py
datahog/db/__init__.py
datahog/db/query.py
datahog/db/txn.py