Metadata-Version: 1.0
Name: datahog
Version: 0.0.2
Summary: a shardable postgresql-backed data store
Home-page: UNKNOWN
Author: UNKNOWN
Author-email: UNKNOWN
License: UNKNOWN
Platform: UNKNOWN
